mcp_get_weather_bayang/__init__.py
mcp_get_weather_bayang/__main__.py
mcp_get_weather_bayang/server.py
mcp_get_weather_bayang-0.1.5.dist-info/METADATA
mcp_get_weather_bayang-0.1.5.dist-info/WHEEL
mcp_get_weather_bayang-0.1.5.dist-info/entry_points.txt
mcp_get_weather_bayang-0.1.5.dist-info/top_level.txt
mcp_get_weather_bayang-0.1.5.dist-info/RECORD
