Metadata-Version: 2.4
Name: mcp-get-weather-bayang
Version: 0.1.5
Summary: 输入OpenWeather-API-KEY，获取天气信息。
Requires-Python: >=3.12
Requires-Dist: httpx>=0.28.1
Requires-Dist: mcp>=1.8.0
